[
    {
        "标题": "民办非企业单位",
        "数据领域": "公共服务",
        "数据类型": "file",
        "创建时间": "2023-01-10",
        "发布时间": "2023-01-10",
        "更新时间": "2023-03-15",
        "主题分类": "生活服务",
        "开放属性": "无条件开发",
        "所属部门": "淮南市民政局",
        "url": "https://sjzyj.huainan.gov.cn/odssite/view/page/govDataFile?pageIndex=file&dataId=1659782716742"
    },
    {
        "标题": "12329热线电话咨询服务",
        "数据领域": "公共服务",
        "数据类型": "table",
        "创建时间": "2023-01-10",
        "发布时间": "2023-01-10",
        "更新时间": "2023-03-15",
        "主题分类": "生活服务",
        "开放属性": "有条件开发",
        "所属部门": "淮南市数据资源管理局",
        "url": "https://sjzyj.huainan.gov.cn/odssite/view/page/govDataFile?pageIndex=table&dataId=1659782716738"
    },
    {
        "标题": "96119火灾隐患举报投诉受理",
        "数据领域": "公共服务",
        "数据类型": "table",
        "创建时间": "2023-01-10",
        "发布时间": "2023-01-10",
        "更新时间": "2023-03-15",
        "主题分类": "生活服务",
        "开放属性": "有条件开发",
        "所属部门": "淮南市数据资源管理局",
        "url": "https://sjzyj.huainan.gov.cn/odssite/view/page/govDataFile?pageIndex=table&dataId=1659782716739"
    },
    {
        "标题": "安徽省广播电视精品专项奖励资金核拨",
        "数据领域": "公共服务",
        "数据类型": "table",
        "创建时间": "2023-01-10",
        "发布时间": "2023-01-10",
        "更新时间": "2023-03-15",
        "主题分类": "生活服务",
        "开放属性": "有条件开发",
        "所属部门": "淮南市数据资源管理局",
        "url": "https://sjzyj.huainan.gov.cn/odssite/view/page/govDataFile?pageIndex=table&dataId=1659782716740"
    },
    {
        "标题": "被征地农民养老保险待遇办理",
        "数据领域": "公共服务",
        "数据类型": "table",
        "创建时间": "2023-01-10",
        "发布时间": "2023-01-10",
        "更新时间": "2023-03-17",
        "主题分类": "生活服务",
        "开放属性": "有条件开发",
        "所属部门": "淮南市数据资源管理局",
        "url": "https://sjzyj.huainan.gov.cn/odssite/view/page/govDataFile?pageIndex=table&dataId=1659782716741"
    },
    {
        "标题": "全市住房公积金运行情况",
        "数据领域": "公共服务",
        "数据类型": "file",
        "创建时间": "2023-01-09",
        "发布时间": "2023-01-10",
        "更新时间": "2023-01-10",
        "主题分类": "民生保障",
        "开放属性": "无条件开发",
        "所属部门": "淮南市住房公积金管理中心",
        "url": "https://sjzyj.huainan.gov.cn/odssite/view/page/govDataFile?pageIndex=file&dataId=1659782716718"
    },
    {
        "标题": "淮南市住房公积金年度报告",
        "数据领域": "公共服务",
        "数据类型": "file",
        "创建时间": "2023-01-09",
        "发布时间": "2023-01-10",
        "更新时间": "2023-01-10",
        "主题分类": "民生保障",
        "开放属性": "无条件开发",
        "所属部门": "淮南市住房公积金管理中心",
        "url": "https://sjzyj.huainan.gov.cn/odssite/view/page/govDataFile?pageIndex=file&dataId=1659782716719"
    },
    {
        "标题": "淮南市古树名木名单",
        "数据领域": "公共服务",
        "数据类型": "file",
        "创建时间": "2023-01-09",
        "发布时间": "2023-01-10",
        "更新时间": "2023-01-10",
        "主题分类": "生态环境",
        "开放属性": "无条件开发",
        "所属部门": "淮南市林业局",
        "url": "https://sjzyj.huainan.gov.cn/odssite/view/page/govDataFile?pageIndex=file&dataId=1659782716706"
    },
    {
        "标题": "淮南市国家级、省级林业龙头企业名单",
        "数据领域": "公共服务",
        "数据类型": "file",
        "创建时间": "2023-01-09",
        "发布时间": "2023-01-10",
        "更新时间": "2023-01-11",
        "主题分类": "生态环境",
        "开放属性": "无条件开发",
        "所属部门": "淮南市林业局",
        "url": "https://sjzyj.huainan.gov.cn/odssite/view/page/govDataFile?pageIndex=file&dataId=1659782716707"
    },
    {
        "标题": "淮南月度经济运行监测",
        "数据领域": "经济发展",
        "数据类型": "file",
        "创建时间": "2023-01-09",
        "发布时间": "2023-01-10",
        "更新时间": "2023-01-10",
        "主题分类": "生活服务",
        "开放属性": "无条件开发",
        "所属部门": "淮南市统计局",
        "url": "https://sjzyj.huainan.gov.cn/odssite/view/page/govDataFile?pageIndex=file&dataId=1659782716679"
    },
    {
        "标题": "中小型科技企业",
        "数据领域": "经济发展",
        "数据类型": "file",
        "创建时间": "2023-01-09",
        "发布时间": "2023-01-10",
        "更新时间": "2023-01-10",
        "主题分类": "科技创新",
        "开放属性": "无条件开发",
        "所属部门": "淮南市科技局",
        "url": "https://sjzyj.huainan.gov.cn/odssite/view/page/govDataFile?pageIndex=file&dataId=1659782716709"
    },
    {
        "标题": "国家重点实验室",
        "数据领域": "经济发展",
        "数据类型": "file",
        "创建时间": "2023-01-09",
        "发布时间": "2023-01-10",
        "更新时间": "2023-01-10",
        "主题分类": "科技创新",
        "开放属性": "无条件开发",
        "所属部门": "淮南市科技局",
        "url": "https://sjzyj.huainan.gov.cn/odssite/view/page/govDataFile?pageIndex=file&dataId=1659782716710"
    },
    {
        "标题": "历年高新技术企业信息",
        "数据领域": "经济发展",
        "数据类型": "file",
        "创建时间": "2023-01-09",
        "发布时间": "2023-01-10",
        "更新时间": "2023-01-10",
        "主题分类": "科技创新",
        "开放属性": "无条件开发",
        "所属部门": "淮南市科技局",
        "url": "https://sjzyj.huainan.gov.cn/odssite/view/page/govDataFile?pageIndex=file&dataId=1659782716711"
    },
    {
        "标题": "施工许可信息",
        "数据领域": "政务机构",
        "数据类型": "file",
        "创建时间": "2023-01-09",
        "发布时间": "2023-01-10",
        "更新时间": "2023-01-10",
        "主题分类": "城建住房",
        "开放属性": "无条件开发",
        "所属部门": "淮南市住房和城乡建设局",
        "url": "https://sjzyj.huainan.gov.cn/odssite/view/page/govDataFile?pageIndex=file&dataId=1659782716676"
    },
    {
        "标题": "月度全省各市社会及工业用电量",
        "数据领域": "经济发展",
        "数据类型": "api",
        "创建时间": "2023-01-10",
        "发布时间": "2023-01-10",
        "更新时间": "2023-03-15",
        "主题分类": "生活服务",
        "开放属性": "有条件开发",
        "所属部门": "淮南市统计局",
        "url": "https://sjzyj.huainan.gov.cn/odssite/view/page/govDataFile?pageIndex=api&dataId=1659782716728"
    },
    {
        "标题": "月度全省各市常住居民人均可支配收入",
        "数据领域": "经济发展",
        "数据类型": "api",
        "创建时间": "2023-01-10",
        "发布时间": "2023-01-10",
        "更新时间": "2023-03-15",
        "主题分类": "生活服务",
        "开放属性": "有条件开发",
        "所属部门": "淮南市统计局",
        "url": "https://sjzyj.huainan.gov.cn/odssite/view/page/govDataFile?pageIndex=api&dataId=1659782716727"
    },
    {
        "标题": "月度全省各市各类投资",
        "数据领域": "经济发展",
        "数据类型": "api",
        "创建时间": "2023-01-10",
        "发布时间": "2023-01-10",
        "更新时间": "2023-03-22",
        "主题分类": "生活服务",
        "开放属性": "有条件开发",
        "所属部门": "淮南市统计局",
        "url": "https://sjzyj.huainan.gov.cn/odssite/view/page/govDataFile?pageIndex=api&dataId=1659782716726"
    },
    {
        "标题": "省级“专精特新”中小企业信息",
        "数据领域": "经济发展",
        "数据类型": "file",
        "创建时间": "2023-01-09",
        "发布时间": "2023-01-09",
        "更新时间": "2023-01-11",
        "主题分类": "工业农业",
        "开放属性": "无条件开发",
        "所属部门": "淮南市经济和信息化局",
        "url": "https://sjzyj.huainan.gov.cn/odssite/view/page/govDataFile?pageIndex=file&dataId=1659782716721"
    },
    {
        "标题": "企业亩均评价结果信息",
        "数据领域": "经济发展",
        "数据类型": "file",
        "创建时间": "2023-01-09",
        "发布时间": "2023-01-09",
        "更新时间": "2023-01-09",
        "主题分类": "工业农业",
        "开放属性": "无条件开发",
        "所属部门": "淮南市经济和信息化局",
        "url": "https://sjzyj.huainan.gov.cn/odssite/view/page/govDataFile?pageIndex=file&dataId=1659782716724"
    },
    {
        "标题": "水资源公报",
        "数据领域": "政务机构",
        "数据类型": "file",
        "创建时间": "2023-01-08",
        "发布时间": "2023-01-08",
        "更新时间": "2023-01-08",
        "主题分类": "生态环境",
        "开放属性": "无条件开发",
        "所属部门": "淮南市水利局",
        "url": "https://sjzyj.huainan.gov.cn/odssite/view/page/govDataFile?pageIndex=file&dataId=1659782716664"
    },
    {
        "标题": "淮南市环境无害化销毁能力单位名录",
        "数据领域": "政务机构",
        "数据类型": "file",
        "创建时间": "2023-01-08",
        "发布时间": "2023-01-08",
        "更新时间": "2023-01-11",
        "主题分类": "生态环境",
        "开放属性": "无条件开发",
        "所属部门": "淮南市生态环境局",
        "url": "https://sjzyj.huainan.gov.cn/odssite/view/page/govDataFile?pageIndex=file&dataId=1659782716663"
    },
    {
        "标题": "淮南市2023年度工伤保险定点机构名单",
        "数据领域": "公共服务",
        "数据类型": "file",
        "创建时间": "2023-01-08",
        "发布时间": "2023-01-08",
        "更新时间": "2023-03-15",
        "主题分类": "民生保障",
        "开放属性": "无条件开发",
        "所属部门": "淮南市人力资源和社会保障局",
        "url": "https://sjzyj.huainan.gov.cn/odssite/view/page/govDataFile?pageIndex=file&dataId=1659782716653"
    },
    {
        "标题": "市级环境影响评价审批信息",
        "数据领域": "政务机构",
        "数据类型": "file",
        "创建时间": "2023-01-08",
        "发布时间": "2023-01-08",
        "更新时间": "2023-01-11",
        "主题分类": "生态环境",
        "开放属性": "无条件开发",
        "所属部门": "淮南市生态环境局",
        "url": "https://sjzyj.huainan.gov.cn/odssite/view/page/govDataFile?pageIndex=file&dataId=1659782716654"
    },
    {
        "标题": "排污许可证发放情况",
        "数据领域": "政务机构",
        "数据类型": "file",
        "创建时间": "2023-01-08",
        "发布时间": "2023-01-08",
        "更新时间": "2023-03-15",
        "主题分类": "生态环境",
        "开放属性": "无条件开发",
        "所属部门": "淮南市生态环境局",
        "url": "https://sjzyj.huainan.gov.cn/odssite/view/page/govDataFile?pageIndex=file&dataId=1659782716655"
    },
    {
        "标题": "环境质量月报",
        "数据领域": "政务机构",
        "数据类型": "file",
        "创建时间": "2023-01-08",
        "发布时间": "2023-01-08",
        "更新时间": "2023-03-15",
        "主题分类": "生态环境",
        "开放属性": "无条件开发",
        "所属部门": "淮南市生态环境局",
        "url": "https://sjzyj.huainan.gov.cn/odssite/view/page/govDataFile?pageIndex=file&dataId=1659782716656"
    },
    {
        "标题": "集中式生活饮用水水源水质状况",
        "数据领域": "政务机构",
        "数据类型": "file",
        "创建时间": "2023-01-08",
        "发布时间": "2023-01-08",
        "更新时间": "2023-03-15",
        "主题分类": "生态环境",
        "开放属性": "无条件开发",
        "所属部门": "淮南市生态环境局",
        "url": "https://sjzyj.huainan.gov.cn/odssite/view/page/govDataFile?pageIndex=file&dataId=1659782716657"
    },
    {
        "标题": "辐射安全许可证办理信息",
        "数据领域": "政务机构",
        "数据类型": "file",
        "创建时间": "2023-01-08",
        "发布时间": "2023-01-08",
        "更新时间": "2023-03-15",
        "主题分类": "生态环境",
        "开放属性": "无条件开发",
        "所属部门": "淮南市生态环境局",
        "url": "https://sjzyj.huainan.gov.cn/odssite/view/page/govDataFile?pageIndex=file&dataId=1659782716658"
    },
    {
        "标题": "降尘监测结果表",
        "数据领域": "政务机构",
        "数据类型": "file",
        "创建时间": "2023-01-08",
        "发布时间": "2023-01-08",
        "更新时间": "2023-03-15",
        "主题分类": "生态环境",
        "开放属性": "无条件开发",
        "所属部门": "淮南市生态环境局",
        "url": "https://sjzyj.huainan.gov.cn/odssite/view/page/govDataFile?pageIndex=file&dataId=1659782716659"
    },
    {
        "标题": "淮南市环境质量状况公报",
        "数据领域": "政务机构",
        "数据类型": "file",
        "创建时间": "2023-01-08",
        "发布时间": "2023-01-08",
        "更新时间": "2023-01-08",
        "主题分类": "生态环境",
        "开放属性": "无条件开发",
        "所属部门": "淮南市生态环境局",
        "url": "https://sjzyj.huainan.gov.cn/odssite/view/page/govDataFile?pageIndex=file&dataId=1659782716660"
    },
    {
        "标题": "淮南市危险废物经营许可证汇总统计",
        "数据领域": "政务机构",
        "数据类型": "file",
        "创建时间": "2023-01-08",
        "发布时间": "2023-01-08",
        "更新时间": "2023-01-08",
        "主题分类": "生态环境",
        "开放属性": "无条件开发",
        "所属部门": "淮南市生态环境局",
        "url": "https://sjzyj.huainan.gov.cn/odssite/view/page/govDataFile?pageIndex=file&dataId=1659782716661"
    },
    {
        "标题": "淮南市年度重点排污单位名录",
        "数据领域": "政务机构",
        "数据类型": "file",
        "创建时间": "2023-01-08",
        "发布时间": "2023-01-08",
        "更新时间": "2023-01-08",
        "主题分类": "生态环境",
        "开放属性": "无条件开发",
        "所属部门": "淮南市生态环境局",
        "url": "https://sjzyj.huainan.gov.cn/odssite/view/page/govDataFile?pageIndex=file&dataId=1659782716662"
    },
    {
        "标题": "社会保障卡综合服务站",
        "数据领域": "公共服务",
        "数据类型": "file",
        "创建时间": "2023-01-08",
        "发布时间": "2023-01-08",
        "更新时间": "2023-03-15",
        "主题分类": "民生保障",
        "开放属性": "无条件开发",
        "所属部门": "淮南市人力资源和社会保障局",
        "url": "https://sjzyj.huainan.gov.cn/odssite/view/page/govDataFile?pageIndex=file&dataId=1659782716652"
    },
    {
        "标题": "粮油全品种收购进度",
        "数据领域": "公共服务",
        "数据类型": "file",
        "创建时间": "2023-01-08",
        "发布时间": "2023-01-08",
        "更新时间": "2023-03-15",
        "主题分类": "民生保障",
        "开放属性": "无条件开发",
        "所属部门": null,
        "url": "https://sjzyj.huainan.gov.cn/odssite/view/page/govDataFile?pageIndex=file&dataId=1659782716650"
    },
    {
        "标题": "“安徽好粮油”产品名单",
        "数据领域": "公共服务",
        "数据类型": "file",
        "创建时间": "2023-01-08",
        "发布时间": "2023-01-08",
        "更新时间": "2023-03-15",
        "主题分类": "民生保障",
        "开放属性": "无条件开发",
        "所属部门": null,
        "url": "https://sjzyj.huainan.gov.cn/odssite/view/page/govDataFile?pageIndex=file&dataId=1659782716651"
    },
    {
        "标题": "省技术创新示范企业认定信息",
        "数据领域": "经济发展",
        "数据类型": "file",
        "创建时间": "2023-01-08",
        "发布时间": "2023-01-08",
        "更新时间": "2023-03-15",
        "主题分类": "工业农业",
        "开放属性": "无条件开发",
        "所属部门": "淮南市经济和信息化局",
        "url": "https://sjzyj.huainan.gov.cn/odssite/view/page/govDataFile?pageIndex=file&dataId=1659782716649"
    }
]